deployv_static/__init__.py
deployv_static/deployv_static.py
deployv_static/templates/base_dockerfile.jinja
deployv_static/templates/config_lc_collate.jinja
deployv_static/templates/deactivation.jinja
deployv_static/templates/default_config.json
deployv_static/templates/deployv.conf
deployv_static/templates/dev_dockerfile.jinja
deployv_static/templates/dev_instances.jinja
deployv_static/templates/entrypoint_image.jinja
deployv_static/templates/get_release_data.py
deployv_static/templates/getaddons.py
deployv_static/templates/install_deps.py
deployv_static/templates/l10n_mx_edi.certificate.csv
deployv_static/templates/nginx_sites.jinja
deployv_static/templates/odoo_service.jinja
deployv_static/templates/openerp_serverrc
deployv_static/templates/orchestv_default_config.json
deployv_static/templates/postgres_service.jinja
deployv_static/templates/supervisord_service.conf
deployv_static/templates/transitions.json
deployv_static-0.0.66.dist-info/AUTHORS.rst
deployv_static-0.0.66.dist-info/LICENSE
deployv_static-0.0.66.dist-info/METADATA
deployv_static-0.0.66.dist-info/WHEEL
deployv_static-0.0.66.dist-info/top_level.txt
deployv_static-0.0.66.dist-info/RECORD
