Metadata-Version: 2.1
Name: deployv-static
Version: 0.0.66
Summary: DeployV static files: Dockerfiles, json, configs, templates
Home-page: https://github.com/Vauxoo/deployv-static
Author: Vauxoo
Author-email: info@vauxoo.com
License: BSD
Keywords: deployv-static
Classifier: Development Status :: 2 - Pre-Alpha
Classifier: Intended Audience :: Developers
Classifier: License :: OSI Approved :: BSD License
Classifier: Natural Language :: English
Classifier: Programming Language :: Python :: 2
Classifier: Programming Language :: Python :: 2.7
Classifier: Programming Language :: Python :: 3
Classifier: Programming Language :: Python :: 3.5
Classifier: Programming Language :: Python :: 3.6
License-File: LICENSE
License-File: AUTHORS.rst
Requires-Dist: wheel
